LICENSE
MANIFEST.in
README.md
setup.py
sentry_cardinal/__init__.py
sentry_cardinal/interfaces.py
sentry_cardinal.egg-info/PKG-INFO
sentry_cardinal.egg-info/SOURCES.txt
sentry_cardinal.egg-info/dependency_links.txt
sentry_cardinal.egg-info/not-zip-safe
sentry_cardinal.egg-info/top_level.txt
sentry_cardinal/templates/sentry_cardinal/partial/interfaces/stacktrace.html