Metadata-Version: 1.0
Name: sentry-cardinal
Version: 0.1.0-1
Summary: Added niceness for railsy tracebacks in Sentry
Home-page: https://github.com/causes/sentry_cardinal
Author: Noah Silas
Author-email: noah.silas@causes.com
License: MIT
Platform: UNKNOWN
Classifier: Framework :: Django
Classifier: Intended Audience :: Developers
Classifier: Operating System :: OS Independent
Classifier: Programming Language :: Python
Classifier: License :: OSI Approved :: BSD License
Classifier: Development Status :: 3 - Alpha
